pydantic_secret_decimal.py
pydantic_secret_decimal-0.1.2.dist-info/LICENSE
pydantic_secret_decimal-0.1.2.dist-info/WHEEL
pydantic_secret_decimal-0.1.2.dist-info/METADATA
pydantic_secret_decimal-0.1.2.dist-info/RECORD
